gamechain/__init__.py
gamechain/gamechain.py
gamechain/games.py
gamechain/gc_engine.py
gamechain/gc_message.py
gamechain/gc_message_builder.py
gamechain/gc_parser.py
gamechain/gc_state.py
gamechain-0.0.2.dist-info/METADATA
gamechain-0.0.2.dist-info/RECORD
gamechain-0.0.2.dist-info/WHEEL
gamechain-0.0.2.dist-info/top_level.txt
