Metadata-Version: 2.1
Name: gamechain
Version: 0.0.2
Summary: Play and record games on the BCH blockchain
Home-page: https://github.com/devalbo/gamechain
Author: Albert Boehmler
Author-email: ajboehmler@gmail.com
License: UNKNOWN
Platform: UNKNOWN
Classifier: Programming Language :: Python :: 3
Classifier: License :: OSI Approved :: GNU General Public License v3 (GPLv3)
Classifier: Operating System :: OS Independent
